ProgramizKotlinJiaochengChuyiFix1/README.md
ProgramizKotlinJiaochengChuyiFix1/__init__.py
ProgramizKotlinJiaochengChuyiFix1/__main__.py
ProgramizKotlinJiaochengChuyiFix1/file.epub
ProgramizKotlinJiaochengChuyiFix1/index.html
ProgramizKotlinJiaochengChuyiFix1/css/__init__.py
ProgramizKotlinJiaochengChuyiFix1/css/annotations.css
ProgramizKotlinJiaochengChuyiFix1/css/main.css
ProgramizKotlinJiaochengChuyiFix1/css/normalize.css
ProgramizKotlinJiaochengChuyiFix1/css/popup.css
ProgramizKotlinJiaochengChuyiFix1/font/__init__.py
ProgramizKotlinJiaochengChuyiFix1/font/fontello.eot
ProgramizKotlinJiaochengChuyiFix1/font/fontello.svg
ProgramizKotlinJiaochengChuyiFix1/font/fontello.ttf
ProgramizKotlinJiaochengChuyiFix1/font/fontello.woff
ProgramizKotlinJiaochengChuyiFix1/img/__init__.py
ProgramizKotlinJiaochengChuyiFix1/img/annotator-glyph-sprite.png
ProgramizKotlinJiaochengChuyiFix1/img/annotator-icon-sprite.png
ProgramizKotlinJiaochengChuyiFix1/img/apple-touch-icon.png
ProgramizKotlinJiaochengChuyiFix1/img/cancelfullscreen.png
ProgramizKotlinJiaochengChuyiFix1/img/close.png
ProgramizKotlinJiaochengChuyiFix1/img/fullscreen.png
ProgramizKotlinJiaochengChuyiFix1/img/loader.gif
ProgramizKotlinJiaochengChuyiFix1/img/menu-icon.png
ProgramizKotlinJiaochengChuyiFix1/img/save.png
ProgramizKotlinJiaochengChuyiFix1/img/saved.png
ProgramizKotlinJiaochengChuyiFix1/img/settings-s.png
ProgramizKotlinJiaochengChuyiFix1/img/settings.png
ProgramizKotlinJiaochengChuyiFix1/img/star.png
ProgramizKotlinJiaochengChuyiFix1/js/__init__.py
ProgramizKotlinJiaochengChuyiFix1/js/epub.js
ProgramizKotlinJiaochengChuyiFix1/js/epub.min.js
ProgramizKotlinJiaochengChuyiFix1/js/epub.min.map
ProgramizKotlinJiaochengChuyiFix1/js/hooks.min.js
ProgramizKotlinJiaochengChuyiFix1/js/hooks.min.map
ProgramizKotlinJiaochengChuyiFix1/js/reader.js
ProgramizKotlinJiaochengChuyiFix1/js/reader.js.map
ProgramizKotlinJiaochengChuyiFix1/js/reader.min.js
ProgramizKotlinJiaochengChuyiFix1/js/reader.min.map
programiz_kotlin_jiaocheng_chuyi_fix1-2025.3.24.1.dist-info/METADATA
programiz_kotlin_jiaocheng_chuyi_fix1-2025.3.24.1.dist-info/WHEEL
programiz_kotlin_jiaocheng_chuyi_fix1-2025.3.24.1.dist-info/entry_points.txt
programiz_kotlin_jiaocheng_chuyi_fix1-2025.3.24.1.dist-info/top_level.txt
programiz_kotlin_jiaocheng_chuyi_fix1-2025.3.24.1.dist-info/RECORD
